simple_transfer/__init__.py
simple_transfer/column.py
simple_transfer/config.py
simple_transfer/connection.py
simple_transfer/extractor.py
simple_transfer/injector.py
simple_transfer/pipeline.py
simple_transfer/py.typed
simple_transfer/connections/__init__.py
simple_transfer/connections/mysql.py
simple_transfer/connections/postgresql.py
simple_transfer/connections/py.typed
simple_transfer-0.1.1.dist-info/LICENSE
simple_transfer-0.1.1.dist-info/METADATA
simple_transfer-0.1.1.dist-info/WHEEL
simple_transfer-0.1.1.dist-info/top_level.txt
simple_transfer-0.1.1.dist-info/RECORD
