Metadata-Version: 2.1
Name: simple-transfer
Version: 0.1.1
Summary: A tool for moving data between relational databases.
Home-page: https://github.com/henryivesjones/simple-transfer
Author: Henry Jones
Author-email: Henry Jones <henryivesjones@gmail.com>
Keywords: pipeline,postgresql,mysql,data-transfer,relational,data
Classifier: Programming Language :: Python :: 3
Classifier: Operating System :: OS Independent
Requires-Python: >=3.6
License-File: LICENSE
Requires-Dist: psycopg2
Requires-Dist: smart-open
Requires-Dist: mysql-connector-python
